tpulse/__init__.py
tpulse/settings.py
tpulse/sync_client.py
tpulse-0.1.9.dist-info/LICENSE
tpulse-0.1.9.dist-info/WHEEL
tpulse-0.1.9.dist-info/METADATA
tpulse-0.1.9.dist-info/RECORD
