Metadata-Version: 2.1
Name: tpulse
Version: 0.1.9
Summary: version
Author-email: Semenov Artur <juicehq@yandex.ru>
Requires-Python: >=3.7
Classifier: License :: OSI Approved :: MIT License
Requires-Dist: httpx >= 0.21.1
Requires-Dist: fake_useragent >= 0.1.11
Project-URL: Home, https://github.com/meanother/tpulse-py
